forestadmin/datasource_sqlalchemy/__init__.py
forestadmin/datasource_sqlalchemy/collections.py
forestadmin/datasource_sqlalchemy/datasource.py
forestadmin/datasource_sqlalchemy/exceptions.py
forestadmin/datasource_sqlalchemy/interfaces.py
forestadmin/datasource_sqlalchemy/utils/__init__.py
forestadmin/datasource_sqlalchemy/utils/aggregation.py
forestadmin/datasource_sqlalchemy/utils/model_converter.py
forestadmin/datasource_sqlalchemy/utils/query_factory.py
forestadmin/datasource_sqlalchemy/utils/record_serializer.py
forestadmin/datasource_sqlalchemy/utils/relationships.py
forestadmin/datasource_sqlalchemy/utils/type_converter.py
forestadmin_datasource_sqlalchemy-1.23.9.dist-info/METADATA
forestadmin_datasource_sqlalchemy-1.23.9.dist-info/WHEEL
forestadmin_datasource_sqlalchemy-1.23.9.dist-info/RECORD
